{  "timestamp": "2026-04-01T13:00:00+00:00",  "currentPrice": 68614.06,  "ema10": 68430.96,  "ema50": 67575.51,  "gap": 855.44,  "gapPercent": 1.247,  "status": "EMA10 above EMA50 | Converging",  "converging": true,  "imminent": false,  "candles": [    {      "time": "2026-04-01T09:00:00+00:00",      "close": 69061.3,      "ema10": 68200.9,      "ema50": 67394.33,      "gap": 806.57    },    {      "time": "2026-04-01T10:00:00+00:00",      "close": 68645.32,      "ema10": 68281.7,      "ema50": 67443.39,      "gap": 838.32    },    {      "time": "2026-04-01T11:00:00+00:00",      "close": 68613.96,      "ema10": 68342.11,      "ema50": 67489.29,      "gap": 852.82    },    {      "time": "2026-04-01T12:00:00+00:00",      "close": 68606.96,      "ema10": 68390.27,      "ema50": 67533.12,      "gap": 857.14    },    {      "time": "2026-04-01T13:00:00+00:00",      "close": 68614.06,      "ema10": 68430.96,      "ema50": 67575.51,      "gap": 855.44    }  ]}